<annotation>
	<folder>JPEGImages</folder>
	<filename>0007.jpg</filename>
	<path>E:\1A表面检测文件\yolov7-pytorch-master\yolov7-pytorch-master\VOCdevkit\JPEGImages\0007.jpg</path>
	<source>
		<database>Unknown</database>
	</source>
	<size>
		<width>2000</width>
		<height>2000</height>
		<depth>3</depth>
	</size>
	<segmented>0</segmented>
	<object>
		<name>LW</name>
		<pose>Unspecified</pose>
		<truncated>0</truncated>
		<difficult>0</difficult>
		<bndbox>
			<xmin>86</xmin>
			<ymin>371</ymin>
			<xmax>158</xmax>
			<ymax>478</ymax>
		</bndbox>
	</object>
	<object>
		<name>LW</name>
		<pose>Unspecified</pose>
		<truncated>0</truncated>
		<difficult>0</difficult>
		<bndbox>
			<xmin>223</xmin>
			<ymin>273</ymin>
			<xmax>255</xmax>
			<ymax>341</ymax>
		</bndbox>
	</object>
	<object>
		<name>LW</name>
		<pose>Unspecified</pose>
		<truncated>0</truncated>
		<difficult>0</difficult>
		<bndbox>
			<xmin>18</xmin>
			<ymin>534</ymin>
			<xmax>73</xmax>
			<ymax>623</ymax>
		</bndbox>
	</object>
	<object>
		<name>LW</name>
		<pose>Unspecified</pose>
		<truncated>0</truncated>
		<difficult>0</difficult>
		<bndbox>
			<xmin>18</xmin>
			<ymin>802</ymin>
			<xmax>64</xmax>
			<ymax>906</ymax>
		</bndbox>
	</object>
	<object>
		<name>LW</name>
		<pose>Unspecified</pose>
		<truncated>0</truncated>
		<difficult>0</difficult>
		<bndbox>
			<xmin>101</xmin>
			<ymin>1247</ymin>
			<xmax>149</xmax>
			<ymax>1323</ymax>
		</bndbox>
	</object>
	<object>
		<name>LW</name>
		<pose>Unspecified</pose>
		<truncated>1</truncated>
		<difficult>0</difficult>
		<bndbox>
			<xmin>1</xmin>
			<ymin>1639</ymin>
			<xmax>40</xmax>
			<ymax>1689</ymax>
		</bndbox>
	</object>
</annotation>
